common_pkg/__init__.py
common_pkg/fake-UA.py
common_pkg/os.py
common_pkg/web.py
common_pkg/database/__init__.py
common_pkg/database/mysql.py
common_pkg_dennis-0.0.1.dist-info/LICENSE.txt
common_pkg_dennis-0.0.1.dist-info/METADATA
common_pkg_dennis-0.0.1.dist-info/WHEEL
common_pkg_dennis-0.0.1.dist-info/top_level.txt
common_pkg_dennis-0.0.1.dist-info/RECORD
