Metadata-Version: 2.1
Name: common-pkg-dennis
Version: 0.0.1
Summary: a package contains common functions deal with database and video_downloads
Home-page: https://github.com/pypa/sampleproject
Author: dennis
Author-email: yifengchaoran@163.com
License: UNKNOWN
Platform: UNKNOWN
Classifier: Programming Language :: Python :: 3
Classifier: License :: OSI Approved :: MIT License
Classifier: Operating System :: OS Independent
Requires-Python: >=3.6
